exoface/exoface.py
exoface/haarcascade_frontalface_default.xml
exoface-1.1.6.dist-info/METADATA
exoface-1.1.6.dist-info/WHEEL
exoface-1.1.6.dist-info/licenses/LICENSE
exoface-1.1.6.dist-info/RECORD
