Metadata-Version: 2.4
Name: exoface
Version: 1.1.6
Summary: a library for facial recognition(everything from training to recognizing)
Project-URL: Homepage, https://github.com/WeDu-official/exoface
Project-URL: Issues, https://github.com/WeDu-official/exoface/issues
Author-email: WeDu-official <fplu.the.founder@gmail.com>
License-File: LICENSE
Classifier: Development Status :: 6 - Mature
Classifier: Intended Audience :: Developers
Classifier: License :: Other/Proprietary License
Classifier: Natural Language :: English
Classifier: Operating System :: Microsoft :: Windows :: Windows 8.1
Classifier: Operating System :: Microsoft :: Windows :: Windows 10
Classifier: Operating System :: Microsoft :: Windows :: Windows 11
Classifier: Programming Language :: Python :: 3.8
Classifier: Programming Language :: Python :: 3.9
Classifier: Programming Language :: Python :: 3.10
Classifier: Programming Language :: Python :: 3.11
Classifier: Programming Language :: Python :: 3.12
Classifier: Programming Language :: Python :: 3.13
Classifier: Topic :: Home Automation
Classifier: Topic :: Multimedia :: Graphics :: Capture :: Digital Camera
Classifier: Topic :: Multimedia :: Video :: Capture
Classifier: Topic :: Scientific/Engineering :: Image Processing
Classifier: Topic :: Scientific/Engineering :: Image Recognition
Requires-Python: >=3.10
Requires-Dist: numpy>=2.2.3
Requires-Dist: opencv-contrib-python>=4.11.0.86
Requires-Dist: opencv-python>=4.11.0.86
Requires-Dist: pillow>=11.1.0
Requires-Dist: powerdb>=2.1.8
